writemore/__init__.py
writemore/cli.py
writemore/templates.py
writemore/writemore.py
writemore-0.0.1.dist-info/LICENSE
writemore-0.0.1.dist-info/METADATA
writemore-0.0.1.dist-info/WHEEL
writemore-0.0.1.dist-info/entry_points.txt
writemore-0.0.1.dist-info/RECORD
