Metadata-Version: 2.1
Name: writemore
Version: 0.0.1
Summary: 
Author: Giorgio Patrini
Requires-Python: >=3.10,<4.0
Classifier: Programming Language :: Python :: 3
Classifier: Programming Language :: Python :: 3.10
Classifier: Programming Language :: Python :: 3.11
Requires-Dist: click (==8.1.3)
Requires-Dist: langchain (==0.0.137)
Requires-Dist: openai (==0.27.4)
Requires-Dist: pydantic (>=1.10.7,<2.0.0)
Requires-Dist: tiktoken (>=0.3.3,<0.4.0)
